pydanticV2_argparse/__init__.py
pydanticV2_argparse/actions.py
pydanticV2_argparse/parser.py
pydanticV2_argparse/patches.py
pydanticV2_argparse/utils.py
pydanticv2_argparse-1.0.5.dist-info/licenses/LICENSE.md
pydanticv2_argparse-1.0.5.dist-info/METADATA
pydanticv2_argparse-1.0.5.dist-info/WHEEL
pydanticv2_argparse-1.0.5.dist-info/RECORD
