Metadata-Version: 2.4
Name: pydanticV2-argparse
Version: 1.0.5
Summary: Typed Argument Parsing with Pydantic
License-Expression: MIT
License-File: LICENSE.md
Keywords: python,pydantic,argparse,typed,validation
Author: HUANGYI QIN
Author-email: qinhunagyi@gmail.com
Requires-Python: >=3.8
Classifier: Programming Language :: Python :: 3
Classifier: Programming Language :: Python :: 3.8
Classifier: Programming Language :: Python :: 3.9
Classifier: Programming Language :: Python :: 3.10
Classifier: Programming Language :: Python :: 3.11
Classifier: Programming Language :: Python :: 3.12
Classifier: Programming Language :: Python :: 3.13
Classifier: Programming Language :: Python :: 3.14
Requires-Dist: pydantic (>=2.10.0)
Requires-Dist: pydantic-settings (>=2.8.1)
Project-URL: Homepage, https://github.com/qinhy/pydanticV2-argparse
Project-URL: Repository, https://github.com/qinhy/pydanticV2-argparse
